<annotation>
	<folder>Imagenes_generadas</folder>
	<filename>78.jpg</filename>
	<path>/home/mau/Mytest/P_R_D/Imagenes_generadas/78.jpg</path>
	<source>
		<database>Unknown</database>
	</source>
	<size>
		<width>600</width>
		<height>600</height>
		<depth>3</depth>
	</size>
	<segmented>0</segmented>
	<object>
		<name>componente_T</name>
		<pose>Unspecified</pose>
		<truncated>0</truncated>
		<difficult>0</difficult>
		<bndbox>
			<xmin>422</xmin>
			<ymin>288</ymin>
			<xmax>517</xmax>
			<ymax>379</ymax>
		</bndbox>
	</object>
</annotation>
